{
  "powers": [
    "spellrigins:lightning/lightning_bonus_specialist",
    "spellrigins:lightning/lightningsummon",
    "spellrigins:lon/lossofknowledge_fire",
    "spellrigins:lon/lossofknowledge_holy",
    "spellrigins:lon/lossofknowledge_blood",
    "spellrigins:lon/lossofknowledge_eldritch",
    "spellrigins:lon/lossofknowledge_evocation",
    "spellrigins:lon/lossofknowledge_ender",
    "spellrigins:lon/lossofknowledge_nature",
    "spellrigins:lon/lossofknowledge_aqua",
    "spellrigins:lon/lossofknowledge_ice",
    "spellrigins:lon/lossofknowledge"
  ],
  "icon": "irons_spellbooks:lightning_upgrade_orb",
  "order": 11,
  "impact": 3,
  "name": "Lightning Specialist",
  "description": "You would be foolish to not fear my power"
}